{
  "telegram": "https://t.me/vaathala1",
  "last update time": "12:57 am 17-08-2025",
  "stream": [
    {
      "source_url": "https://bq32.short.gy/O7fkma",
      "stream_url1": "https://usher.ttvnw.net/api/channel/hls/jstcheel.m3u8?acmb=eyJBcHBWZXJzaW9uIjoiODc3YjBhMmYtYTY2Yi00MDBmLTk1ODUtOTlmZDIxZTQwN2NiIn0%3D&allow_source=true&browser_family=chrome&browser_version=121.0&cdm=wv&fast_bread=true&include_unavailable=true&os_name=Linux&os_version=undefined&p=6855077&platform=web&play_session_id=f66af3b13890e18884bbecf5d2562228&player_backend=mediaplayer&player_version=1.43.0-rc.4&playlist_include_framerate=true&reassignments_supported=true&sig=62a64ff13c02b4673027778a09062a3825437d8e&supported_codecs=av1,h264&token=%7B%22adblock%22%3Afalse%2C%22authorization%22%3A%7B%22forbidden%22%3Afalse%2C%22reason%22%3A%22%22%7D%2C%22blackout_enabled%22%3Afalse%2C%22channel%22%3A%22jstcheel%22%2C%22channel_id%22%3A1066424752%2C%22chansub%22%3A%7B%22restricted_bitrates%22%3A%5B%5D%2C%22view_until%22%3A1924905600%7D%2C%22ci_gb%22%3Afalse%2C%22geoblock_reason%22%3A%22%22%2C%22device_id%22%3A%22ru48gc4kvdt6olGKar7YpLMX8DMMjxnd%22%2C%22expires%22%3A1755373566%2C%22extended_history_allowed%22%3Afalse%2C%22game%22%3A%22%22%2C%22hide_ads%22%3Afalse%2C%22https_required%22%3Atrue%2C%22mature%22%3Afalse%2C%22partner%22%3Afalse%2C%22platform%22%3A%22web%22%2C%22player_type%22%3A%22site%22%2C%22private%22%3A%7B%22allowed_to_view%22%3Atrue%7D%2C%22privileged%22%3Afalse%2C%22role%22%3A%22%22%2C%22server_ads%22%3Atrue%2C%22show_ads%22%3Atrue%2C%22subscriber%22%3Afalse%2C%22turbo%22%3Afalse%2C%22user_id%22%3Anull%2C%22user_ip%22%3A%2252.159.247.194%22%2C%22version%22%3A3%2C%22maximum_resolution%22%3A%22FULL_HD%22%2C%22maximum_video_bitrate_kbps%22%3A12500%2C%22maximum_resolution_reasons%22%3A%7B%22QUAD_HD%22%3A%5B%22AUTHZ_NOT_LOGGED_IN%22%5D%2C%22ULTRA_HD%22%3A%5B%22AUTHZ_NOT_LOGGED_IN%22%5D%7D%2C%22maximum_video_bitrate_kbps_reasons%22%3A%5B%22AUTHZ_DISALLOWED_BITRATE%22%5D%7D&transcode_mode=cbr_v1"
    },
    {
      "source_url": "https://www.twitch.tv/heyimenbhizeebal?sr=a",
      "stream_url2": "https://usher.ttvnw.net/api/channel/hls/heyimenbhizeebal.m3u8?acmb=eyJBcHBWZXJzaW9uIjoiODc3YjBhMmYtYTY2Yi00MDBmLTk1ODUtOTlmZDIxZTQwN2NiIn0%3D&allow_source=true&browser_family=chrome&browser_version=121.0&cdm=wv&fast_bread=true&include_unavailable=true&os_name=Linux&os_version=undefined&p=826220&platform=web&play_session_id=cdb07abe98d73d76514569dd16cc062e&player_backend=mediaplayer&player_version=1.43.0-rc.4&playlist_include_framerate=true&reassignments_supported=true&sig=a24a3f888dc78790353a2a27045d45a9f2458136&supported_codecs=av1,h264&token=%7B%22adblock%22%3Afalse%2C%22authorization%22%3A%7B%22forbidden%22%3Afalse%2C%22reason%22%3A%22%22%7D%2C%22blackout_enabled%22%3Afalse%2C%22channel%22%3A%22heyimenbhizeebal%22%2C%22channel_id%22%3A1166557876%2C%22chansub%22%3A%7B%22restricted_bitrates%22%3A%5B%5D%2C%22view_until%22%3A1924905600%7D%2C%22ci_gb%22%3Afalse%2C%22geoblock_reason%22%3A%22%22%2C%22device_id%22%3A%22ru48gc4kvdt6olGKar7YpLMX8DMMjxnd%22%2C%22expires%22%3A1755373583%2C%22extended_history_allowed%22%3Afalse%2C%22game%22%3A%22%22%2C%22hide_ads%22%3Afalse%2C%22https_required%22%3Atrue%2C%22mature%22%3Afalse%2C%22partner%22%3Afalse%2C%22platform%22%3A%22web%22%2C%22player_type%22%3A%22site%22%2C%22private%22%3A%7B%22allowed_to_view%22%3Atrue%7D%2C%22privileged%22%3Afalse%2C%22role%22%3A%22%22%2C%22server_ads%22%3Atrue%2C%22show_ads%22%3Atrue%2C%22subscriber%22%3Afalse%2C%22turbo%22%3Afalse%2C%22user_id%22%3Anull%2C%22user_ip%22%3A%2252.159.247.194%22%2C%22version%22%3A3%2C%22maximum_resolution%22%3A%22FULL_HD%22%2C%22maximum_video_bitrate_kbps%22%3A12500%2C%22maximum_resolution_reasons%22%3A%7B%22QUAD_HD%22%3A%5B%22AUTHZ_NOT_LOGGED_IN%22%5D%2C%22ULTRA_HD%22%3A%5B%22AUTHZ_NOT_LOGGED_IN%22%5D%7D%2C%22maximum_video_bitrate_kbps_reasons%22%3A%5B%22AUTHZ_DISALLOWED_BITRATE%22%5D%7D&transcode_mode=cbr_v1"
    },
    {
      "source_url": "https://www.twitch.tv/kukeeku",
      "stream_url3": "https://usher.ttvnw.net/api/channel/hls/kukeeku.m3u8?acmb=eyJBcHBWZXJzaW9uIjoiODc3YjBhMmYtYTY2Yi00MDBmLTk1ODUtOTlmZDIxZTQwN2NiIn0%3D&allow_source=true&browser_family=chrome&browser_version=121.0&cdm=wv&fast_bread=true&include_unavailable=true&os_name=Linux&os_version=undefined&p=5934397&platform=web&play_session_id=7dc07ad569e6111abadf79c0a393bef7&player_backend=mediaplayer&player_version=1.43.0-rc.4&playlist_include_framerate=true&reassignments_supported=true&sig=466ddb23512e43cf6e74996e6fa4c75d9edff9b1&supported_codecs=av1,h264&token=%7B%22adblock%22%3Afalse%2C%22authorization%22%3A%7B%22forbidden%22%3Afalse%2C%22reason%22%3A%22%22%7D%2C%22blackout_enabled%22%3Afalse%2C%22channel%22%3A%22kukeeku%22%2C%22channel_id%22%3A1348470171%2C%22chansub%22%3A%7B%22restricted_bitrates%22%3A%5B%5D%2C%22view_until%22%3A1924905600%7D%2C%22ci_gb%22%3Afalse%2C%22geoblock_reason%22%3A%22%22%2C%22device_id%22%3A%22ru48gc4kvdt6olGKar7YpLMX8DMMjxnd%22%2C%22expires%22%3A1755373601%2C%22extended_history_allowed%22%3Afalse%2C%22game%22%3A%22%22%2C%22hide_ads%22%3Afalse%2C%22https_required%22%3Atrue%2C%22mature%22%3Afalse%2C%22partner%22%3Afalse%2C%22platform%22%3A%22web%22%2C%22player_type%22%3A%22site%22%2C%22private%22%3A%7B%22allowed_to_view%22%3Atrue%7D%2C%22privileged%22%3Afalse%2C%22role%22%3A%22%22%2C%22server_ads%22%3Atrue%2C%22show_ads%22%3Atrue%2C%22subscriber%22%3Afalse%2C%22turbo%22%3Afalse%2C%22user_id%22%3Anull%2C%22user_ip%22%3A%2252.159.247.194%22%2C%22version%22%3A3%2C%22maximum_resolution%22%3A%22FULL_HD%22%2C%22maximum_video_bitrate_kbps%22%3A12500%2C%22maximum_resolution_reasons%22%3A%7B%22QUAD_HD%22%3A%5B%22AUTHZ_NOT_LOGGED_IN%22%5D%2C%22ULTRA_HD%22%3A%5B%22AUTHZ_NOT_LOGGED_IN%22%5D%7D%2C%22maximum_video_bitrate_kbps_reasons%22%3A%5B%22AUTHZ_DISALLOWED_BITRATE%22%5D%7D&transcode_mode=cbr_v1"
    },
    {
      "source_url": "https://bigbosslive.com/live/",
      "stream_url4": "https://bigbosslive.com/live/stream.m3u8"
    }
  ]
}